aigerox-0.11.0.dist-info/METADATA
aigerox-0.11.0.dist-info/WHEEL
aigerox/__init__.py
aigerox/aigerox.abi3.so
aigerox-0.11.0.dist-info/RECORD
