Metadata-Version: 2.4
Name: aigerox
Version: 0.11.0
Summary: A Rust library for working with AIGs (And-Inverted Graphs) and AIGER files.
Author: Konstantin Chukharev <lipen00@gmail.com>
Author-email: Konstantin Chukharev <lipen00@gmail.com>
Project-URL: Source Code, https://github.com/Lipen/aigerox
